[{"n":"Abia","lat":5.4318,"lon":7.4883},{"n":"Adamawa","lat":9.1626,"lon":12.2916},{"n":"Akwa Ibom","lat":4.9905,"lon":7.7956},{"n":"Anambra","lat":6.2485,"lon":6.9379},{"n":"Bauchi","lat":10.9979,"lon":9.3258},{"n":"Bayelsa","lat":4.8268,"lon":5.9511},{"n":"Benue","lat":7.3009,"lon":8.8124},{"n":"Borno","lat":11.8701,"lon":13.4276},{"n":"Cross River","lat":5.7913,"lon":8.4034},{"n":"Delta","lat":5.7566,"lon":5.4997},{"n":"Ebonyi","lat":6.2398,"lon":8.0667},{"n":"Edo","lat":6.6654,"lon":5.8737},{"n":"Ekiti","lat":7.6952,"lon":5.2979},{"n":"Enugu","lat":6.5198,"lon":7.3928},{"n":"Federal Capital Territory","lat":9.0131,"lon":7.191},{"n":"Gombe","lat":10.4306,"lon":11.2247},{"n":"Imo","lat":5.5657,"lon":7.0332},{"n":"Jigawa","lat":11.9811,"lon":9.6249},{"n":"Kaduna","lat":10.2572,"lon":7.8594},{"n":"Kano","lat":11.5731,"lon":8.5434},{"n":"Katsina","lat":12.2362,"lon":7.5003},{"n":"Kebbi","lat":11.6908,"lon":3.9661},{"n":"Kogi","lat":7.6364,"lon":6.8492},{"n":"Kwara","lat":9.0935,"lon":4.5669},{"n":"Lagos","lat":6.5346,"lon":3.7116},{"n":"Nasarawa","lat":8.5892,"lon":8.211},{"n":"Niger","lat":9.7736,"lon":5.7114},{"n":"Ogun","lat":7.1274,"lon":3.2628},{"n":"Ondo","lat":6.8241,"lon":4.8694},{"n":"Osun","lat":7.5381,"lon":4.5211},{"n":"Oyo","lat":8.1354,"lon":3.613},{"n":"Plateau","lat":9.3802,"lon":9.6282},{"n":"Rivers","lat":5.0233,"lon":6.8358},{"n":"Sokoto","lat":12.7395,"lon":5.237},{"n":"Taraba","lat":8.0586,"lon":10.3863},{"n":"Yobe","lat":11.9736,"lon":11.5242},{"n":"Zamfara","lat":12.013,"lon":6.051}]